monetdb_pystethoscope/__init__.py
monetdb_pystethoscope/api.py
monetdb_pystethoscope/connection/__init__.py
monetdb_pystethoscope/connection/api.py
monetdb_pystethoscope/filtering.py
monetdb_pystethoscope/formatting.py
monetdb_pystethoscope/obfuscation.py
monetdb_pystethoscope/parsing.py
monetdb_pystethoscope/stethoscope.py
monetdb_pystethoscope/transformers.py
monetdb_pystethoscope/utilities.py
monetdb_pystethoscope-0.3.2.dist-info/entry_points.txt
monetdb_pystethoscope-0.3.2.dist-info/LICENSE
monetdb_pystethoscope-0.3.2.dist-info/WHEEL
monetdb_pystethoscope-0.3.2.dist-info/METADATA
monetdb_pystethoscope-0.3.2.dist-info/RECORD
