Metadata-Version: 2.1
Name: monetdb-pystethoscope
Version: 0.3.2
Summary: MonetDB profiler connection tool
Home-page: https://github.com/MonetDBSolutions/monetdb-pystethoscope
Author: Panagiotis Koutsourakis
Author-email: kutsurak@monetdbsolutions.com
Requires-Python: >=3.5,<4.0
Classifier: Programming Language :: Python :: 3
Classifier: Programming Language :: Python :: 3.5
Classifier: Programming Language :: Python :: 3.6
Classifier: Programming Language :: Python :: 3.7
Classifier: Programming Language :: Python :: 3.8
Classifier: Programming Language :: Python :: 3.9
Requires-Dist: pymonetdb (>=1.3.1,<2.0.0)
Project-URL: Repository, https://github.com/MonetDBSolutions/monetdb-pystethoscope
